morphometry/__init__.py
morphometry/__version__.py
morphometry/commons/__init__.py
morphometry/formats/__init__.py
morphometry/freesurfer/__init__.py
morphometry/freesurfer/mri_cnr.py
morphometry/freesurfer/mri_convert.py
morphometry/freesurfer/mris_anatomical_stats.py
morphometry/freesurfer/mris_euler_number.py
morphometry/freesurfer/recon_all.py
morphometry/freesurfer/tal_qc_azs.py
morphometry/freesurfer/wm_anat_snr.py
morphometry/greve/__init__.py
morphometry/greve/mri_convert.py
morphometry/parsers/__init__.py
morphometry/plots/__init__.py
morphometry/snapshots/__init__.py
morphometry/xnat/__init__.py
morphometry/xnat/morph3/__init__.py
morphometry/xnat/morph3/mapping.yml
morphometry-0.2.2.data/scripts/surpher.py
morphometry-0.2.2.dist-info/LICENSE
morphometry-0.2.2.dist-info/METADATA
morphometry-0.2.2.dist-info/WHEEL
morphometry-0.2.2.dist-info/top_level.txt
morphometry-0.2.2.dist-info/RECORD
