Metadata-Version: 2.1
Name: morphometry
Version: 0.2.2
Summary: FreeSurfer E2E pipeline
Home-page: https://github.com/harvard-nrg/morphometry
Author: Neuroinformatics Research Group
Author-email: info@neuroinfo.org
License-File: LICENSE
Requires-Dist: pydicom
Requires-Dist: pyaml
Requires-Dist: lxml
Requires-Dist: pillow
Requires-Dist: nibabel
Requires-Dist: yaxil
Requires-Dist: retry
Requires-Dist: natsort
Requires-Dist: matplotlib
